penngrader/__init__.py
penngrader/backend.py
penngrader/grader.py
penngrader/penngrader.py
penngrader/teacher_backend.py
penngrader-0.4.dist-info/LICENSE
penngrader-0.4.dist-info/METADATA
penngrader-0.4.dist-info/WHEEL
penngrader-0.4.dist-info/top_level.txt
penngrader-0.4.dist-info/RECORD
