Metadata-Version: 2.1
Name: penngrader
Version: 0.4
Summary: In-line python grader client.
Home-page: https://github.com/LeoMurri/PennGrader
Author: Leonardo Murri
Author-email: leonardo.murri1995@gmail.com
License: UNKNOWN
Platform: UNKNOWN
Classifier: Programming Language :: Python :: 3
Classifier: License :: OSI Approved :: MIT License
Classifier: Operating System :: OS Independent
